NiukeKehuduanGangQiuzhiJingyanFenxiang20212022Fix1/README.md
NiukeKehuduanGangQiuzhiJingyanFenxiang20212022Fix1/__init__.py
NiukeKehuduanGangQiuzhiJingyanFenxiang20212022Fix1/__main__.py
NiukeKehuduanGangQiuzhiJingyanFenxiang20212022Fix1/file.epub
NiukeKehuduanGangQiuzhiJingyanFenxiang20212022Fix1/index.html
NiukeKehuduanGangQiuzhiJingyanFenxiang20212022Fix1/css/__init__.py
NiukeKehuduanGangQiuzhiJingyanFenxiang20212022Fix1/css/annotations.css
NiukeKehuduanGangQiuzhiJingyanFenxiang20212022Fix1/css/main.css
NiukeKehuduanGangQiuzhiJingyanFenxiang20212022Fix1/css/normalize.css
NiukeKehuduanGangQiuzhiJingyanFenxiang20212022Fix1/css/popup.css
NiukeKehuduanGangQiuzhiJingyanFenxiang20212022Fix1/font/__init__.py
NiukeKehuduanGangQiuzhiJingyanFenxiang20212022Fix1/font/fontello.eot
NiukeKehuduanGangQiuzhiJingyanFenxiang20212022Fix1/font/fontello.svg
NiukeKehuduanGangQiuzhiJingyanFenxiang20212022Fix1/font/fontello.ttf
NiukeKehuduanGangQiuzhiJingyanFenxiang20212022Fix1/font/fontello.woff
NiukeKehuduanGangQiuzhiJingyanFenxiang20212022Fix1/img/__init__.py
NiukeKehuduanGangQiuzhiJingyanFenxiang20212022Fix1/img/annotator-glyph-sprite.png
NiukeKehuduanGangQiuzhiJingyanFenxiang20212022Fix1/img/annotator-icon-sprite.png
NiukeKehuduanGangQiuzhiJingyanFenxiang20212022Fix1/img/apple-touch-icon.png
NiukeKehuduanGangQiuzhiJingyanFenxiang20212022Fix1/img/cancelfullscreen.png
NiukeKehuduanGangQiuzhiJingyanFenxiang20212022Fix1/img/close.png
NiukeKehuduanGangQiuzhiJingyanFenxiang20212022Fix1/img/fullscreen.png
NiukeKehuduanGangQiuzhiJingyanFenxiang20212022Fix1/img/loader.gif
NiukeKehuduanGangQiuzhiJingyanFenxiang20212022Fix1/img/menu-icon.png
NiukeKehuduanGangQiuzhiJingyanFenxiang20212022Fix1/img/save.png
NiukeKehuduanGangQiuzhiJingyanFenxiang20212022Fix1/img/saved.png
NiukeKehuduanGangQiuzhiJingyanFenxiang20212022Fix1/img/settings-s.png
NiukeKehuduanGangQiuzhiJingyanFenxiang20212022Fix1/img/settings.png
NiukeKehuduanGangQiuzhiJingyanFenxiang20212022Fix1/img/star.png
niuke_kehuduan_gang_qiuzhi_jingyan_fenxiang_2021_2022_fix1-2025.3.25.1.dist-info/METADATA
niuke_kehuduan_gang_qiuzhi_jingyan_fenxiang_2021_2022_fix1-2025.3.25.1.dist-info/WHEEL
niuke_kehuduan_gang_qiuzhi_jingyan_fenxiang_2021_2022_fix1-2025.3.25.1.dist-info/entry_points.txt
niuke_kehuduan_gang_qiuzhi_jingyan_fenxiang_2021_2022_fix1-2025.3.25.1.dist-info/top_level.txt
niuke_kehuduan_gang_qiuzhi_jingyan_fenxiang_2021_2022_fix1-2025.3.25.1.dist-info/RECORD
